locapip/__init__.py
locapip/__main__.py
locapip/_test/__init__.py
locapip/_test/locapip_test.proto
locapip/_test/locapip_test.py
locapip/_test/locapip_test_pb2.py
locapip/_test/locapip_test_pb2_grpc.py
locapip/_test/protoc.bat
locapip/proto/__init__.py
locapip/proto/dicom.proto
locapip/proto/dicom.py
locapip/proto/dicom_pb2.py
locapip/proto/dicom_pb2_grpc.py
locapip/proto/explorer.proto
locapip/proto/explorer.py
locapip/proto/explorer_pb2.py
locapip/proto/explorer_pb2_grpc.py
locapip/proto/fit_fill.proto
locapip/proto/fit_fill.py
locapip/proto/fit_fill_pb2.py
locapip/proto/fit_fill_pb2_grpc.py
locapip/proto/test.proto
locapip/proto/test.py
locapip/proto/test_pb2.py
locapip/proto/test_pb2_grpc.py
locapip-0.1.17.dist-info/LICENSE
locapip-0.1.17.dist-info/METADATA
locapip-0.1.17.dist-info/WHEEL
locapip-0.1.17.dist-info/top_level.txt
locapip-0.1.17.dist-info/RECORD
