Metadata-Version: 2.1
Name: locapip
Version: 0.1.17
Summary: C++ embedded Python microservices
Home-page: https://gitlab.com/locapidio/locapip
Author: sjtu_6547
Author-email: 88172828@qq.com
License: UNKNOWN
Keywords: protobuf grpcio grpcio-tools
Platform: UNKNOWN
Classifier: Development Status :: 4 - Beta
Classifier: Intended Audience :: Developers
Classifier: Framework :: AsyncIO
Classifier: License :: OSI Approved :: GNU General Public License v3 or later (GPLv3+)
Requires-Python: >=3.7
License-File: LICENSE
Requires-Dist: click (>=8)
Requires-Dist: grpcio-tools (>=1.41.0)
